hacs_crewai/__init__.py
hacs_crewai/adapter.py
hacs_crewai/py.typed
hacs_crewai-0.2.2.dist-info/METADATA
hacs_crewai-0.2.2.dist-info/WHEEL
hacs_crewai-0.2.2.dist-info/RECORD
