Metadata-Version: 2.4
Name: hacs-crewai
Version: 0.2.2
Summary: CrewAI adapter for HACS (Healthcare Agent Communication Standard)
Project-URL: Homepage, https://github.com/solanovisitor/hacs
Project-URL: Documentation, https://github.com/solanovisitor/hacs/tree/main/docs
Project-URL: Repository, https://github.com/solanovisitor/hacs
Project-URL: Issues, https://github.com/solanovisitor/hacs/issues
Author-email: HACS Contributors <contributors@hacs.dev>
License-Expression: Apache-2.0
Classifier: Development Status :: 4 - Beta
Classifier: Intended Audience :: Developers
Classifier: Intended Audience :: Healthcare Industry
Classifier: License :: OSI Approved :: Apache Software License
Classifier: Programming Language :: Python :: 3
Classifier: Programming Language :: Python :: 3.10
Classifier: Programming Language :: Python :: 3.11
Classifier: Programming Language :: Python :: 3.12
Classifier: Programming Language :: Python :: 3.13
Classifier: Topic :: Scientific/Engineering :: Artificial Intelligence
Classifier: Topic :: Scientific/Engineering :: Medical Science Apps.
Requires-Python: >=3.10
Requires-Dist: crewai>=0.30.0
Requires-Dist: hacs-core>=0.1.0
Requires-Dist: hacs-models>=0.1.0
Requires-Dist: pydantic>=2.0.0
Provides-Extra: dev
Requires-Dist: mypy>=1.0; extra == 'dev'
Requires-Dist: pytest-asyncio>=0.21; extra == 'dev'
Requires-Dist: pytest-cov>=4.0; extra == 'dev'
Requires-Dist: pytest>=7.0; extra == 'dev'
Requires-Dist: ruff>=0.1.0; extra == 'dev'
